{
    "obj" :{
        "id": "9f68384c73c9483ab480bedc5544f558",
    "title": "All Songs Considered",
    "publisher": "NPR",
    "image": "https://production.listennotes.com/podcasts/all-songs-considered-npr-a1eyImOiglt-jCrdsm1q0Jn.300x300.jpg",
    "thumbnail": "https://production.listennotes.com/podcasts/all-songs-considered-npr-a1eyImOiglt-jCrdsm1q0Jn.300x300.jpg",
    "listennotes_url": "https://www.listennotes.com/c/9f68384c73c9483ab480bedc5544f558/",
    "listen_score": "Please upgrade to PRO or ENTERPRISE plan to see this field",
    "listen_score_global_rank": "Please upgrade to PRO or ENTERPRISE plan to see this field",
    "total_episodes": 426,
    "explicit_content": false,
    "description": "Hosts/nerds Bob Boilen and Robin Hilton are your friendly music buddies with the week's best new music discoveries, including conversations with emerging artists, icons and more. Hear songs that can completely change your day, with humor, heart and (sometimes) a whole lot of noise. Directions for use: Morning commute, the gym, or alone time. (If rash persists, discontinue use.)",
    "itunes_id": 79687345,
    "rss": "Please upgrade to PRO or ENTERPRISE plan to see this field",
    "latest_pub_date_ms": 1629277224000,
    "earliest_pub_date_ms": 1513771268299,
    "language": "English",
    "country": "United States",
    "website": "https://www.npr.org/allsongs?utm_source=listennotes.com&utm_campaign=Listen+Notes&utm_medium=website",
    "extra": {
        "twitter_handle": "",
        "facebook_handle": "",
        "instagram_handle": "",
        "wechat_handle": "",
        "patreon_handle": "",
        "youtube_url": "",
        "linkedin_url": "",
        "spotify_url": "",
        "google_url": "",
        "url1": "",
        "url2": "",
        "url3": ""
    },
    "is_claimed": false,
    "email": "Please upgrade to PRO or ENTERPRISE plan to see this field",
    "type": "episodic",
    "looking_for": {
        "sponsors": false,
        "guests": false,
        "cohosts": false,
        "cross_promotion": false
    },
    "genre_ids": [
        134,
        132,
        122,
        67
    ],
    "episodes": [
        {
            "id": "379696d223c447f1a032240262c5c75f",
            "title": "Guest DJ: Rodrigo Amarante",
            "description": "The great Brazilian-born, now Los Angeles-based musician has just put out <em>Drama</em>, his first solo album in seven years. We also hear music that changed his life, including songs from The Smiths and Gilberto Gil.",
            "pub_date_ms": 1629277224000,
            "audio": "https://www.listennotes.com/e/p/379696d223c447f1a032240262c5c75f/",
            "audio_length_sec": 2995,
            "listennotes_url": "https://www.listennotes.com/e/379696d223c447f1a032240262c5c75f/",
            "image": "https://production.listennotes.com/podcasts/all-songs-considered/guest-dj-rodrigo-amarante-1k3t_ACdSNo-CsU0nKb8-il.300x168.jpg",
            "thumbnail": "https://production.listennotes.com/podcasts/all-songs-considered/guest-dj-rodrigo-amarante-1k3t_ACdSNo-CsU0nKb8-il.300x168.jpg",
            "maybe_audio_invalid": false,
            "listennotes_edit_url": "https://www.listennotes.com/e/379696d223c447f1a032240262c5c75f/#edit",
            "explicit_content": false,
            "link": "https://www.npr.org/2021/08/17/1028563631/guest-dj-rodrigo-amarante?utm_source=listennotes.com&utm_campaign=Listen+Notes&utm_medium=website",
            "guid_from_rss": "1c986936-f28f-424c-8ae3-235d047f9cad"
        },
        {
            "id": "9d7c79bee33e441dade446e3ccd3b329",
            "title": "Tiny Desk Contest Top Shelf: Our Favorite 2021 Entries, Episode 4",
            "description": "Before we announce this year's Tiny Desk Contest winner, we're asking our judges to share their favorite entries in a weekly livestreamed series. In this episode, John Morrison shares his picks.",
            "pub_date_ms": 1629104435000,
            "audio": "https://www.listennotes.com/e/p/9d7c79bee33e441dade446e3ccd3b329/",
            "audio_length_sec": 2343,
            "listennotes_url": "https://www.listennotes.com/e/9d7c79bee33e441dade446e3ccd3b329/",
            "image": "https://production.listennotes.com/podcasts/all-songs-considered/tiny-desk-contest-top-shelf-mENITDhSWOP-ybqFMhtp0rG.300x168.jpg",
            "thumbnail": "https://production.listennotes.com/podcasts/all-songs-considered/tiny-desk-contest-top-shelf-mENITDhSWOP-ybqFMhtp0rG.300x168.jpg",
            "maybe_audio_invalid": false,
            "listennotes_edit_url": "https://www.listennotes.com/e/9d7c79bee33e441dade446e3ccd3b329/#edit",
            "explicit_content": false,
            "link": "https://www.npr.org/2021/08/09/1026101947/tiny-desk-contest-top-shelf-our-favorite-2021-entries-episode-4?utm_source=listennotes.com&utm_campaign=Listen+Notes&utm_medium=website",
            "guid_from_rss": "6daefcef-ec54-4baf-9341-7ecb4f7bd127"
        },
        {
            "id": "da1b17cc74ae47e6b77ed58a3851967a",
            "title": "New Music Friday: Aug. 13",
            "description": "Black Thought guests on a new one from the British duo Jungle, The Killers' <em>Pressure Machine</em> documents the hopes and horrors of rural America, Boldy James & The Alchemist team up again and more.<br/><br/>Featured Albums:<br/>1. Jungle — <em>Loving in Stereo</em><br/>Featured Songs: \"Talk About It\" and \"Romeo\"<br/>2. The Killers — <em>Pressure Machine</em><br/>Featured Songs: \"Terrible Thing\" and \"West Hills\"<br/>3. Boldy James & The Alchemist — <em>Bo Jackson</em><br/>Featured Song: \"E.P.M.D.\"<br/>4. Falkner Evans — <em>Invisible Words</em><br/>Featured Song: \"Made Visible\"<br/>5. Meet Me @ The Altar — <em>Model Citizen</em><br/>Featured Song: \"Feel A Thing\"<br/>6. El Michels Affair Meets Liam Bailey — <em>Ekundayo Inversions</em><br/>Featured Songs: \"Conquer & Divide\" and \"Intro\"<br/>7. Wednesday — <em>Twin Plagues</em><br/>Featured Songs: \"Toothache\" and \"Twin Plagues\"<br/><br/>Other notable releases for Aug. 13: Dan + Shay  — <em>Good Things</em>; Devendra Banhart and Noah Georgeson — <em>Refuge</em>; Jade Bird — <em>Different Kinds of Light</em>; Joy Orbison — <em>Still Slipping Vol. 1</em>; $uicideboy$ — <em>Long Term Effects of SUFFERING.</em>",
            "pub_date_ms": 1628845209000,
            "audio": "https://www.listennotes.com/e/p/da1b17cc74ae47e6b77ed58a3851967a/",
            "audio_length_sec": 2033,
            "listennotes_url": "https://www.listennotes.com/e/da1b17cc74ae47e6b77ed58a3851967a/",
            "image": "https://production.listennotes.com/podcasts/all-songs-considered/new-music-friday-aug-13-2w_VJxA3DRz-e8o-fDbE6NL.300x168.jpg",
            "thumbnail": "https://production.listennotes.com/podcasts/all-songs-considered/new-music-friday-aug-13-2w_VJxA3DRz-e8o-fDbE6NL.300x168.jpg",
            "maybe_audio_invalid": false,
            "listennotes_edit_url": "https://www.listennotes.com/e/da1b17cc74ae47e6b77ed58a3851967a/#edit",
            "explicit_content": false,
            "link": "https://www.npr.org/2021/08/10/1026391898/new-music-friday-the-top-7-albums-out-on-aug-13?utm_source=listennotes.com&utm_campaign=Listen+Notes&utm_medium=website",
            "guid_from_rss": "00f2a3c5-8846-46ec-b78e-5b7d1668d700"
        },
        {
            "id": "25ca65585f8543b7a77c363a8e81ee52",
            "title": "Tiny Desk Contest Top Shelf: Our Favorite 2021 Entries, Episode 3",
            "description": "Before we announce this year's Tiny Desk Contest winner, we're asking our judges to share their favorite entries in a weekly livestreamed series. In this episode, Tobe Nwigwe shares his picks.",
            "pub_date_ms": 1628499605000,
            "audio": "https://www.listennotes.com/e/p/25ca65585f8543b7a77c363a8e81ee52/",
            "audio_length_sec": 2015,
            "listennotes_url": "https://www.listennotes.com/e/25ca65585f8543b7a77c363a8e81ee52/",
            "image": "https://production.listennotes.com/podcasts/all-songs-considered/tiny-desk-contest-top-shelf-84kqwoypa0d-3LSoPfI9u2E.300x168.jpg",
            "thumbnail": "https://production.listennotes.com/podcasts/all-songs-considered/tiny-desk-contest-top-shelf-84kqwoypa0d-3LSoPfI9u2E.300x168.jpg",
            "maybe_audio_invalid": false,
            "listennotes_edit_url": "https://www.listennotes.com/e/25ca65585f8543b7a77c363a8e81ee52/#edit",
            "explicit_content": false,
            "link": "https://www.npr.org/2021/08/02/1023952263/tiny-desk-contest-top-shelf-our-favorite-2021-entries-episode-3?utm_source=listennotes.com&utm_campaign=Listen+Notes&utm_medium=website",
            "guid_from_rss": "b96a0896-8d22-4cc1-a4d0-1d7d7d8cb43a"
        },
        {
            "id": "9f5ccca3b9714cfba291e797fbb5a309",
            "title": "New Music Friday: Aug. 6",
            "description": "NPR Music's picks for the best albums out this week include new ones from the R&B singer Tinashe, composer Max Richter and the greatest rap duo you've never heard of, Abstract Mindstate. <br/><br/>Featured Albums:<br/>1. Abstract Mindstate — <em>Dreams Still Inspire</em><br/>Featured Track: \"I Feel Good\" <br/>2. Max Richter — <em>Exiles</em><br/>Featured Tracks: \"Flowers Of Herself\" and \"Exiles\"<br/>3. Laura Stevenson — <em>Laura Stevenson</em><br/>Featured Tracks: \"State\" and \"Mary\"<br/>4. Tinashe — <em>333</em><br/>Featured Track: \"333\"<br/>5. Fuubutsushi — <em>Natsukashii</em><br/>Featured Track: \"Suzushii Kaze\"<br/>6. Lingua Ignota — <em>Sinner Get Ready</em><br/>Featured Tracks: \"Pennsylvania Furnace\" and \"The Order of Spiritual Virgins\"<br/><br/>Other notable releases for Aug. 6: Barbra Streisand — <em>Release Me 2</em>; Eluvium — <em>Virga II</em>; Moritz Von Oswald Trio — <em>Dissent</em>; Ty Segal — <em>Harmonizer</em>.",
            "pub_date_ms": 1628240414000,
            "audio": "https://www.listennotes.com/e/p/9f5ccca3b9714cfba291e797fbb5a309/",
            "audio_length_sec": 1711,
            "listennotes_url": "https://www.listennotes.com/e/9f5ccca3b9714cfba291e797fbb5a309/",
            "image": "https://production.listennotes.com/podcasts/all-songs-considered/new-music-friday-aug-6-zyCqf6TIaPu-DIkE-PYWR8O.300x168.jpg",
            "thumbnail": "https://production.listennotes.com/podcasts/all-songs-considered/new-music-friday-aug-6-zyCqf6TIaPu-DIkE-PYWR8O.300x168.jpg",
            "maybe_audio_invalid": false,
            "listennotes_edit_url": "https://www.listennotes.com/e/9f5ccca3b9714cfba291e797fbb5a309/#edit",
            "explicit_content": false,
            "link": "https://www.npr.org/2021/08/03/1024216742/new-music-friday-the-top-6-albums-out-on-aug-6?utm_source=listennotes.com&utm_campaign=Listen+Notes&utm_medium=website",
            "guid_from_rss": "5b343095-e064-472d-afac-a1e43d56ec4a"
        },
        {
            "id": "cb08d3cea90d48a4af55be344eeb3e9a",
            "title": "The Best Music Of July: NPR Staff Picks",
            "description": "In July, we found solace in veterans (Billy Bragg) and newcomers (Canary Room), witnessed personal transformations from IDK and WILLOW, hit funky grooves with William Parker and heard angels become mortal in a collaboration between Sufjan Stevens and Angelo De Augustine. <br/><br/>Songs heard in this episode: <br/>• Billy Bragg: \"I Will Be Your Shield\" from <em>The Million Things That Never Happened</em><br/>• Sufjan Stevens & Angelo De Augustine: \"Reach Out\" from <em>A Beginner's Mind</em><br/>• Canary Room: \"Christine\" from <em>Christine</em><br/>• WILLOW: \"don't SAVE ME\" from <em>lately I feel EVERYTHING</em><br/>• IDK: \"Hey Auntie\" from <em>USEE4YOURSELF </em><br/>• William Parker: \"Tabasco\" from <em>Mayan Space Station</em><br/><br/>Follow the <a href=\"https://www.npr.org/series/1002643619/now-playing\">#NowPlaying blog</a> for the NPR Music staff's favorite new songs.",
            "pub_date_ms": 1627981229000,
            "audio": "https://www.listennotes.com/e/p/cb08d3cea90d48a4af55be344eeb3e9a/",
            "audio_length_sec": 1697,
            "listennotes_url": "https://www.listennotes.com/e/cb08d3cea90d48a4af55be344eeb3e9a/",
            "image": "https://production.listennotes.com/podcasts/all-songs-considered/the-best-music-of-july-npr-Asq7bOnS1mg-ZBIMQj5YD7i.300x168.jpg",
            "thumbnail": "https://production.listennotes.com/podcasts/all-songs-considered/the-best-music-of-july-npr-Asq7bOnS1mg-ZBIMQj5YD7i.300x168.jpg",
            "maybe_audio_invalid": false,
            "listennotes_edit_url": "https://www.listennotes.com/e/cb08d3cea90d48a4af55be344eeb3e9a/#edit",
            "explicit_content": false,
            "link": "https://www.npr.org/2021/07/29/1022234536/the-best-music-of-july-npr-staff-picks?utm_source=listennotes.com&utm_campaign=Listen+Notes&utm_medium=website",
            "guid_from_rss": "0261ea39-2f13-4214-b220-6678188f94ad"
        },
        {
            "id": "c7567096924a4340a204a485f26449e0",
            "title": "Tiny Desk Contest Top Shelf: Our Favorite 2021 Entries, Episode 2",
            "description": "Before we announce this year's Tiny Desk Contest winner, we're asking our judges to share their favorite entries in a weekly livestreamed series. In this episode, Phoebe Bridgers shares her picks.",
            "pub_date_ms": 1627894858000,
            "audio": "https://www.listennotes.com/e/p/c7567096924a4340a204a485f26449e0/",
            "audio_length_sec": 2860,
            "listennotes_url": "https://www.listennotes.com/e/c7567096924a4340a204a485f26449e0/",
            "image": "https://production.listennotes.com/podcasts/all-songs-considered/tiny-desk-contest-top-shelf-0VDsqjM9ToI-JfU3FY0Ourp.300x168.jpg",
            "thumbnail": "https://production.listennotes.com/podcasts/all-songs-considered/tiny-desk-contest-top-shelf-0VDsqjM9ToI-JfU3FY0Ourp.300x168.jpg",
            "maybe_audio_invalid": false,
            "listennotes_edit_url": "https://www.listennotes.com/e/c7567096924a4340a204a485f26449e0/#edit",
            "explicit_content": false,
            "link": "https://www.npr.org/2021/07/29/1022244060/tiny-desk-contest-top-shelf-our-favorite-2021-entries-episode-2?utm_source=listennotes.com&utm_campaign=Listen+Notes&utm_medium=website",
            "guid_from_rss": "1289913f-2238-4717-9198-f4ef26863b16"
        },
        {
            "id": "122c0f467212494d87aff84653372f2a",
            "title": "New Music Friday: July 30",
            "description": "The sophomore full-length from Billie Eilish tops our shortlist of the best new albums out this week, along with a posthumous Prince record, Jack Antonoff's Bleachers, the singer Yola and more.<br/><br/>Featured Albums: <br/>1. Billie Eilish — <em>Happier Than Ever </em><br/>Featured Song: \"NDA\"<br/>2. Isaiah Rashad — <em>The House Is Burning</em><br/>Featured Songs: \"True Story\" and \"HB2U\"<br/>3. Bleachers — <em>Take the Sadness Out Of Saturday Night</em><br/>Featured Songs: \"Stop Making This Hurt\" and \"91\"<br/>4. Los Lobos — <em>Native Sons</em><br/>Featured Song: \"The World Is A Ghetto\"<br/>5. Prince — <em>Welcome 2 America</em><br/>Featured Song: \"One Day We Will All Be Free\"<br/>6. Torres — <em>Thirstier</em><br/>Featured Song: \"Are You Sleep Walking?\"<br/>7. Yola — <em>Stand For Myself</em><br/>Featured Song: \"If I Had To Do It All Again\"<br/>8. Skirts — <em>Great Big Wild Oak</em><br/>Featured Song: \"Easy\"<br/><br/>Other notable releases for July 30: Leela James — <em>See Me</em>; LUMP — <em>Animal</em>; Naia Izumi —<em> A Residency in the Los Angeles Area</em>; Poise — <em>Vestiges</em>; Son Volt — Electro Melodier.",
            "pub_date_ms": 1627635626000,
            "audio": "https://www.listennotes.com/e/p/122c0f467212494d87aff84653372f2a/",
            "audio_length_sec": 2050,
            "listennotes_url": "https://www.listennotes.com/e/122c0f467212494d87aff84653372f2a/",
            "image": "https://production.listennotes.com/podcasts/all-songs-considered/new-music-friday-july-30-5k02fTEKaGN-6cJwNAE4GO_.300x168.jpg",
            "thumbnail": "https://production.listennotes.com/podcasts/all-songs-considered/new-music-friday-july-30-5k02fTEKaGN-6cJwNAE4GO_.300x168.jpg",
            "maybe_audio_invalid": false,
            "listennotes_edit_url": "https://www.listennotes.com/e/122c0f467212494d87aff84653372f2a/#edit",
            "explicit_content": false,
            "link": "https://www.npr.org/2021/07/29/1022328221/new-music-friday-the-top-8-albums-out-on-july-30?utm_source=listennotes.com&utm_campaign=Listen+Notes&utm_medium=website",
            "guid_from_rss": "3d47debd-1b70-4dee-80b7-1ef9f0b11c10"
        },
        {
            "id": "21bfe372600048779e909da76e1679a3",
            "title": "New Mix: Steady Holiday, Ada Lea, Wet Leg, More",
            "description": "<em>All Songs Considered </em>host Bob Boilen's favorite new tracks of the week include an amped-up Steady Holiday, late-'70s, post-punk sounds from Gustaf and Wet Leg, the calming guitar of Lanterna and more.<br/><br/>Featured Songs:<br/>1. Steady Holiday: \"Love Me 2\" (Single)<br/>2. Gustaf: \"Book,\" from <em>Audio Drag For Ego Slobs</em><br/>3. Wet Leg: \"Chaise Longue\" (Single)<br/>4. Ada Lea: \"damn,\" from <em>one hand on the steering wheel the other sewing a garden</em><br/>5. The Colorist Orchestra & Howe Gelb (feat. Pieta Brown): \"Sweet Pretender,\" from <em>Not On The Map</em><br/>6. AHI: \"Danger,\" from <em>Prospect</em><br/>7. Lanterna: \"Aix,\" from <em>Hidden Drives</em>",
            "pub_date_ms": 1627462808000,
            "audio": "https://www.listennotes.com/e/p/21bfe372600048779e909da76e1679a3/",
            "audio_length_sec": 2201,
            "listennotes_url": "https://www.listennotes.com/e/21bfe372600048779e909da76e1679a3/",
            "image": "https://production.listennotes.com/podcasts/all-songs-considered/new-mix-steady-holiday-ada-lmRzk4sOMXH-GuSWRHILnQv.300x168.jpg",
            "thumbnail": "https://production.listennotes.com/podcasts/all-songs-considered/new-mix-steady-holiday-ada-lmRzk4sOMXH-GuSWRHILnQv.300x168.jpg",
            "maybe_audio_invalid": false,
            "listennotes_edit_url": "https://www.listennotes.com/e/21bfe372600048779e909da76e1679a3/#edit",
            "explicit_content": false,
            "link": "https://www.npr.org/new-mix-steady-holiday-ada-lea-wet-leg-more?utm_source=listennotes.com&utm_campaign=Listen+Notes&utm_medium=website",
            "guid_from_rss": "3fc9c919-7c01-4663-988d-83f1a29229a9"
        },
        {
            "id": "6cfc83fd81ee41c09451b5cad0988a48",
            "title": "Tiny Desk Contest Top Shelf: Our Favorite 2021 Entries, Episode 1",
            "description": "Before we announce this year's Tiny Desk Contest winner, we're asking our judges to share their favorite entries in a weekly livestreamed series. First up: Tiny Desk producer Bobby Carter.",
            "pub_date_ms": 1627309856000,
            "audio": "https://www.listennotes.com/e/p/6cfc83fd81ee41c09451b5cad0988a48/",
            "audio_length_sec": 2479,
            "listennotes_url": "https://www.listennotes.com/e/6cfc83fd81ee41c09451b5cad0988a48/",
            "image": "https://production.listennotes.com/podcasts/all-songs-considered/tiny-desk-contest-top-shelf-w-U37lJR6fr-mfaoHjQrqNI.300x168.jpg",
            "thumbnail": "https://production.listennotes.com/podcasts/all-songs-considered/tiny-desk-contest-top-shelf-w-U37lJR6fr-mfaoHjQrqNI.300x168.jpg",
            "maybe_audio_invalid": false,
            "listennotes_edit_url": "https://www.listennotes.com/e/6cfc83fd81ee41c09451b5cad0988a48/#edit",
            "explicit_content": false,
            "link": "https://www.npr.org/2021/07/16/1016855650/tiny-desk-contest-top-shelf-our-favorite-2021-entries-episode-1?utm_source=listennotes.com&utm_campaign=Listen+Notes&utm_medium=website",
            "guid_from_rss": "eceaaa93-d106-40ce-9bde-0f9bb51f0fa7"
        }
    ],
    "next_episode_pub_date": 1627309856000
    }
}